dicc/__init__.py
dicc-0.1.0.dist-info/METADATA
dicc-0.1.0.dist-info/WHEEL
dicc-0.1.0.dist-info/RECORD
