Metadata-Version: 2.1
Name: dicc
Version: 0.1.0
Summary: Terminal dictionary and thesaurus, using the Merriam-Webster dictionary API.
Author: acbuie
Author-email: aidancbuie@gmail.com
Requires-Python: >=3.12,<4.0
Classifier: Programming Language :: Python :: 3
Classifier: Programming Language :: Python :: 3.12
